<?xml version="1.0" encoding="UTF-8"?>
<monster name="Elekid" nameDescription="an elekid" race="electric" experience="350" speed="210" manacost="0">
  <health now="60" max="60"/>
  <look type="738" head="15" body="25" legs="95" feet="113" corpse="3285"/>
	<targetchange interval="2000" chance="0"/>
<strategy attack="100" defense="0"/>
  <flags>
    <flag summonable="1"/>
    <flag attackable="1"/>
    <flag hostile="1"/>
    <flag illusionable="1"/>
    <flag convinceable="1"/>
    <flag pushable="1"/>
    <flag canpushitems="0"/>
    <flag canpushcreatures="0"/>
    <flag targetdistance="1"/>
    <flag staticattack="90"/>
    <flag runonhealth="0"/>
   
</flags>
  <attacks>
        <attack name="melee" interval="2000" chance="100" range="1" min="-50" max="-100"/>
        <attack name="Quick Attack" interval="2617" chance="30" range="2"/>
        <attack name="Thunder Punch" interval="2946" chance="28" range="1"/>
        <attack name="Thunder Shock" interval="2852" chance="29" range="3"/>
        <attack name="Thunder Bolt" interval="3040" chance="28" range="4"/>
        <attack name="Thunder Wave" interval="2993" chance="28" range="6"/>
        <attack name="Thunder" interval="3933" chance="22" range="6"/>
    </attacks>
  <defenses armor="0" defense="0"/>
<voices interval="5000" chance="10">
	<voice sentence="ELEE!"/>
<voice sentence="KIIID!"/>
<voice sentence="ELEKID!"/>
  </voices>
 <loot>
         <item id="12198" chance="4000" count="1" countmax="1"/> --imans
        <item id="12176" chance="5000" countmax="1"/> --electric box
    </loot>
<script>
<event name="Spawn"/>
</script>
</monster>